simputils/events/__init__.py
simputils/events/abstract/Eventful.py
simputils/events/abstract/__init__.py
simputils/events/components/BasicEvent.py
simputils/events/components/BasicEventCall.py
simputils/events/components/BasicEventResult.py
simputils/events/components/__init__.py
simputils/events/exceptions/InterruptEventSequence.py
simputils/events/exceptions/__init__.py
simputils/events/types.py
simputils_events-0.1.0.dist-info/WHEEL
simputils_events-0.1.0.dist-info/METADATA
simputils_events-0.1.0.dist-info/RECORD
