Metadata-Version: 2.4
Name: simputils-events
Version: 0.1.0
Summary: Infrastructure for attaching events to objects
Keywords: event,events,simputils,primitives
Author: PandaHugMonster
Author-email: PandaHugMonster <ivan.ponomarev.pi@gmail.com>
License-Expression: MIT
Classifier: Development Status :: 3 - Alpha
Classifier: Intended Audience :: Developers
Classifier: Topic :: Software Development :: Libraries
Classifier: Programming Language :: Python :: 3
Classifier: Programming Language :: Python :: 3.12
Classifier: Programming Language :: Python :: 3.13
Classifier: Programming Language :: Python :: 3.14
Requires-Python: >=3.12
